README.md
setup.py
flake8_tuple_unpack_limit/__init__.py
flake8_tuple_unpack_limit.egg-info/PKG-INFO
flake8_tuple_unpack_limit.egg-info/SOURCES.txt
flake8_tuple_unpack_limit.egg-info/dependency_links.txt
flake8_tuple_unpack_limit.egg-info/entry_points.txt
flake8_tuple_unpack_limit.egg-info/not-zip-safe
flake8_tuple_unpack_limit.egg-info/requires.txt
flake8_tuple_unpack_limit.egg-info/top_level.txt