Metadata-Version: 2.1
Name: flake8-tuple-unpack-limit
Version: 0.0.1
Summary: A flake8 extension that checks for tuple unpack length
Home-page: https://github.com/Dedefer/flake8-tuple-unpack-limit
Author: Danila Fomin
Author-email: ddf1998@gmail.com
License: MIT
Keywords: flake8 tuple unpack limit
Platform: UNKNOWN
Classifier: Environment :: Console
Classifier: Framework :: Flake8
Classifier: Operating System :: OS Independent
Classifier: Topic :: Software Development :: Documentation
Classifier: Topic :: Software Development :: Libraries :: Python Modules
Classifier: Topic :: Software Development :: Quality Assurance
Classifier: Programming Language :: Python
Classifier: Programming Language :: Python :: 3.6
Classifier: Programming Language :: Python :: 3.7
Classifier: Programming Language :: Python :: 3.8
